acertmgr/__init__.py
acertmgr/__main__.py
acertmgr/configuration.py
acertmgr/tools.py
acertmgr/authority/__init__.py
acertmgr/authority/acme.py
acertmgr/authority/v1.py
acertmgr/authority/v2.py
acertmgr/modes/__init__.py
acertmgr/modes/abstract.py
acertmgr/modes/standalone.py
acertmgr/modes/webdir.py
acertmgr/modes/dns/__init__.py
acertmgr/modes/dns/abstract.py
acertmgr/modes/dns/nsupdate.py
acertmgr-1.0.6.data/data/readme/README.md
acertmgr-1.0.6.dist-info/LICENSE
acertmgr-1.0.6.dist-info/METADATA
acertmgr-1.0.6.dist-info/WHEEL
acertmgr-1.0.6.dist-info/entry_points.txt
acertmgr-1.0.6.dist-info/top_level.txt
acertmgr-1.0.6.dist-info/RECORD
