Metadata-Version: 2.1
Name: acertmgr
Version: 1.0.6
Summary: An automated certificate manager using ACME/letsencrypt
Home-page: https://github.com/moepman/acertmgr
Author: Markus Hauschild
Author-email: moepman@binary-kitchen.de
License: ISC
Keywords: acme letsencrypt
Classifier: Development Status :: 5 - Production/Stable
Classifier: Programming Language :: Python
Classifier: Environment :: Console
Classifier: Topic :: Security :: Cryptography
Classifier: License :: OSI Approved :: ISC License (ISCL)
License-File: LICENSE
Requires-Dist: cryptography>=0.6
Provides-Extra: dns
Requires-Dist: dnspython; extra == "dns"
Provides-Extra: ed25519
Requires-Dist: cryptography>=2.6; extra == "ed25519"
Provides-Extra: idna
Requires-Dist: idna; extra == "idna"
Provides-Extra: ocsp-must-staple
Requires-Dist: cryptography>=2.1; extra == "ocsp-must-staple"
Provides-Extra: ocsp-validation
Requires-Dist: cryptography>=2.4; extra == "ocsp-validation"
Provides-Extra: yaml
Requires-Dist: PyYAML; extra == "yaml"
